.gitignore
GPL-V3.0.txt
MANIFEST.in
README.rst
setenv.sh
setup.cfg
setup.py
setup_data.py
Babel/Version.py
Babel/__init__.py
Babel/Application/ApplicationBase.py
Babel/Application/ArgumentParser.py
Babel/Application/Arguments.py
Babel/Application/BabelApplication.py
Babel/Application/Shell.py
Babel/Application/__init__.py
Babel/BibTeX/Entry.py
Babel/BibTeX/Parser.py
Babel/BibTeX/__init__.py
Babel/Config/ConfigFile.py
Babel/Config/ConfigInstall.py
Babel/Config/DefaultConfig.py
Babel/Config/Messages.py
Babel/Config/__init__.py
Babel/Config/logging.yml
Babel/Corpus/ConsoleSearch.py
Babel/Corpus/CorpusRegistry.py
Babel/Corpus/DocumentWords.py
Babel/Corpus/LanguageId.py
Babel/Corpus/Tags.py
Babel/Corpus/__init__.py
Babel/Corpus/BritishNationalCorpus/Tags.py
Babel/Corpus/BritishNationalCorpus/__init__.py
Babel/Corpus/FrenchCorpus/Tags.py
Babel/Corpus/FrenchCorpus/__init__.py
Babel/DataBase/DataBase.py
Babel/DataBase/MysqlDataBase.py
Babel/DataBase/SqlAlchemyBase.py
Babel/DataBase/SqlTableModel.py
Babel/DataBase/SqliteDataBase.py
Babel/DataBase/VersionTable.py
Babel/DataBase/WhooshDatabase.py
Babel/DataBase/__init__.py
Babel/DataBase/CorpusDataBase/__init__.py
Babel/DataBase/DocumentDataBase/DocumentRootTable.py
Babel/DataBase/DocumentDataBase/DocumentTable.py
Babel/DataBase/DocumentDataBase/WordTable.py
Babel/DataBase/DocumentDataBase/__init__.py
Babel/DataBase/Types/Choice.py
Babel/DataBase/Types/Path.py
Babel/DataBase/Types/__init__.py
Babel/DataBaseStatistics/__init__.py
Babel/Document/Document.py
Babel/Document/DocumentDirectory.py
Babel/Document/__init__.py
Babel/FileSystem/AutomaticFileRename.py
Babel/FileSystem/File.py
Babel/FileSystem/Shasum.py
Babel/FileSystem/UserXattr.py
Babel/FileSystem/__init__.py
Babel/GUI/__init__.py
Babel/GUI/Base/BabelRessource.py
Babel/GUI/Base/GuiApplicationBase.py
Babel/GUI/Base/MainWindowBase.py
Babel/GUI/Base/__init__.py
Babel/GUI/PdfBrowser/DirectoryListWidget.py
Babel/GUI/PdfBrowser/DirectorySelector.py
squirrel.egg-info/PKG-INFO
squirrel.egg-info/SOURCES.txt
squirrel.egg-info/dependency_links.txt
squirrel.egg-info/not-zip-safe
squirrel.egg-info/requires.txt
squirrel.egg-info/top_level.txt
