Metadata-Version: 1.1
Name: squirrel
Version: 0.1.0
Summary: An Electronic Document Management System
Home-page: https://github.com/FabriceSalvaire/squirrel
Author: Fabrice Salvaire
Author-email: fabrice.salvaire@orange.fr
License: GPLv3
Keywords: electronic document management system pdf bibliography
Platform: any
Classifier: Topic :: Scientific/Engineering
Classifier: Intended Audience :: Education
Classifier: Development Status :: 3 - Alpha
Classifier: License :: OSI Approved :: GNU General Public License v3 (GPLv3)
Classifier: Operating System :: OS Independent
Classifier: Programming Language :: Python :: 3.6
